airflow_rest_api/.data
airflow_rest_api/__init__.py
airflow_rest_api/api.py
airflow_rest_api/data_classes.py
airflow_rest_api/exceptions.py
airflow_rest_api/templates.py
airflow_rest_api/test_api.py
airflow_rest_api/test_data_classes.py
airflow_rest_api/test_templates.py
airflow_rest_api/tests_fixtures.py
airflow_rest_api/utils.py
airflow_rest_api-0.0.0.dist-info/LICENSE
airflow_rest_api-0.0.0.dist-info/METADATA
airflow_rest_api-0.0.0.dist-info/WHEEL
airflow_rest_api-0.0.0.dist-info/top_level.txt
airflow_rest_api-0.0.0.dist-info/RECORD
