Metadata-Version: 2.1
Name: airflow-rest-api
Version: 0.0.0
Summary: Async wrapper for Airflow REST API
Home-page: https://bit.ly/ara-bb
Author: Michael R. Kisel
Author-email: deploy-me@yandex.ru
Maintainer: Michael R. Kisel <deploy-me@yandex.ru>
Maintainer-email: deploy-me@yandex.ru
License: MIT
Download-URL: https://bit.ly/ara-dwnld
Keywords: airflow,airflow rest api,async airflow,async rest api,async api
Platform: any
Classifier: Development Status :: 5 - Production/Stable
Classifier: Framework :: Apache Airflow
Classifier: Framework :: AsyncIO
Classifier: Framework :: aiohttp
Classifier: Intended Audience :: Developers
Classifier: Intended Audience :: Information Technology
Classifier: Intended Audience :: Science/Research
Classifier: Intended Audience :: System Administrators
Classifier: License :: OSI Approved :: MIT License
Classifier: Operating System :: OS Independent
Classifier: Programming Language :: Python
Classifier: Programming Language :: Python :: 3
Classifier: Programming Language :: Python :: 3.7
Classifier: Programming Language :: Python :: 3.8
Classifier: Programming Language :: Python :: 3.9
Classifier: Programming Language :: Python :: 3.10
Classifier: Programming Language :: Python :: 3.11
Classifier: Topic :: File Formats :: JSON
Classifier: Topic :: Internet
Classifier: Topic :: Office/Business :: Scheduling
Classifier: Topic :: Scientific/Engineering
Classifier: Topic :: Software Development :: Code Generators
Requires-Python: <4,>=3.7
Requires-Dist: aiohttp (<4.0.0)
Requires-Dist: pandas (<=2.0.0)
Requires-Dist: tabulate (<=0.9.0)
Requires-Dist: importlib-resources ; python_version < "3.9"
